rwa/__init__.py
rwa/generic.py
rwa/hdf5.py
rwa/lazy.py
rwa/pandas.py
rwa/scipy.py
rwa/sequence.py
rwa/storable.py
rwa_python-0.9.5.dist-info/LICENSE
rwa_python-0.9.5.dist-info/METADATA
rwa_python-0.9.5.dist-info/WHEEL
rwa_python-0.9.5.dist-info/RECORD
