Metadata-Version: 2.1
Name: rwa-python
Version: 0.9.5
Summary: HDF5-based serialization library for Python datatypes
License: Apache 2.0
Author: François Laurent
Author-email: francois.laurent@pasteur.fr
Requires-Python: >=3.8,<4.0
Classifier: License :: Other/Proprietary License
Classifier: Programming Language :: Python :: 3
Classifier: Programming Language :: Python :: 3.8
Classifier: Programming Language :: Python :: 3.9
Classifier: Programming Language :: Python :: 3.10
Classifier: Programming Language :: Python :: 3.11
Classifier: Programming Language :: Python :: 3.12
Classifier: Programming Language :: Python :: 3.13
Requires-Dist: h5py (>=3,<4)
Requires-Dist: numpy (>=0)
Requires-Dist: pandas (>=0)
Requires-Dist: scipy (>=0)
Requires-Dist: six (>=1.16.0,<2.0.0)
